kmatch/__init__.py
kmatch/kmatch.py
kmatch/mixins.py
kmatch/version.py
kmatch/tests/__init__.py
kmatch/tests/kmatch_tests.py
kmatch/tests/mixin_tests.py
kmatch-0.5.0.dist-info/LICENSE
kmatch-0.5.0.dist-info/METADATA
kmatch-0.5.0.dist-info/WHEEL
kmatch-0.5.0.dist-info/top_level.txt
kmatch-0.5.0.dist-info/RECORD
