Metadata-Version: 2.1
Name: kmatch
Version: 0.5.0
Summary: A language for matching/validating/filtering Python dictionaries
Home-page: https://github.com/ambitioninc/kmatch
Author: Wes Kendall
Author-email: opensource@ambition.com
License: MIT
Keywords: matching,dictionaries,filtering,validation
Platform: UNKNOWN
Classifier: Programming Language :: Python :: 3.7
Classifier: Programming Language :: Python :: 3.8
Classifier: Programming Language :: Python :: 3.9
Classifier: Intended Audience :: Developers
Classifier: License :: OSI Approved :: MIT License
Classifier: Operating System :: OS Independent
Classifier: Development Status :: 5 - Production/Stable
